rm_lite/__init__.py
rm_lite/_version.py
rm_lite/_version.pyi
rm_lite/data/__init__.py
rm_lite/data/tests/__init__.py
rm_lite/data/tests/complex_noise_bad.npy
rm_lite/data/tests/complex_spectrum_bad_fit.npy
rm_lite/data/tests/complex_spectrum_bad_peak.npy
rm_lite/data/tests/complex_spectrum_overflow.npy
rm_lite/data/tests/complex_spectrum_zero_div.npy
rm_lite/data/tests/stokes_i_arr_bad_fit.npy
rm_lite/data/tests/stokes_i_arr_overflow.npy
rm_lite/data/tests/stokes_i_error_arr_bad.npy
rm_lite/tools_1d/__init__.py
rm_lite/tools_1d/bwdepol.py
rm_lite/tools_1d/bwpredict.py
rm_lite/tools_1d/qufit.py
rm_lite/tools_1d/rmclean.py
rm_lite/tools_1d/rmsynth.py
rm_lite/tools_1d/models_ns/__init__.py
rm_lite/tools_1d/models_ns/m1.py
rm_lite/tools_1d/models_ns/m11.py
rm_lite/tools_1d/models_ns/m111.py
rm_lite/tools_1d/models_ns/m2.py
rm_lite/tools_1d/models_ns/m3.py
rm_lite/tools_1d/models_ns/m4.py
rm_lite/tools_1d/models_ns/m5.py
rm_lite/tools_1d/models_ns/m6.py
rm_lite/tools_1d/models_ns/m7.py
rm_lite/tools_3d/__init__.py
rm_lite/tools_3d/fitcube.py
rm_lite/tools_3d/peak_fit.py
rm_lite/tools_3d/rescale_model.py
rm_lite/tools_3d/rmclean.py
rm_lite/tools_3d/rmsynth.py
rm_lite/utils/__init__.py
rm_lite/utils/arrays.py
rm_lite/utils/clean.py
rm_lite/utils/fitting.py
rm_lite/utils/logging.py
rm_lite/utils/multiscale.py
rm_lite/utils/synthesis.py
rm_lite/utils/types.py
rm_lite-2025.5.1.dist-info/METADATA
rm_lite-2025.5.1.dist-info/WHEEL
rm_lite-2025.5.1.dist-info/licenses/LICENSE
rm_lite-2025.5.1.dist-info/RECORD
